{"is_source_file": true, "format": "Python", "description": "Django admin configuration file for registering models to the admin interface.", "external_files": ["django.contrib.admin"], "external_methods": [], "published": [], "classes": [], "methods": [], "calls": [], "search-terms": ["admin", "register", "django", "models"], "state": 2, "file_id": 18, "knowledge_revision": 36, "git_revision": "b6c13351df3aad8b9b0062e7d7561e5a259262fe", "ctags": [], "hash": "e3dc717de887db03a015667a5fec59d8", "format-version": 4, "code-base-name": "notes_backend", "filename": "notes_backend/api/admin.py", "revision_history": [{"36": "b6c13351df3aad8b9b0062e7d7561e5a259262fe"}]}